LICENSE
MANIFEST.in
README.md
setup.py
Kunai.egg-info/PKG-INFO
Kunai.egg-info/SOURCES.txt
Kunai.egg-info/dependency_links.txt
Kunai.egg-info/not-zip-safe
Kunai.egg-info/requires.txt
Kunai.egg-info/top_level.txt
bin/init.d/kunai
etc/default.json
etc/dns.json
etc/graphite.json
etc/haproxy.json
etc/http.json
etc/local.json
etc/mfkey.priv
etc/mfkey.pub
etc/ping.json
etc/statsd.json
etc/websocket.json
etc/debian/apt.json
etc/generators/haproxy.cfg
etc/generators/haproxy.json
etc/linux/disks.json
etc/linux/kernel-stats.py
etc/linux/libs.json
etc/linux/load-average.json
etc/linux/mailq.json
etc/linux/memory.json
etc/linux/ntp.json
etc/linux/running-kernel.json
etc/linux/swap.json
etc/mongodb/chunks_balance.json
etc/mongodb/collection_indexes.json
etc/mongodb/collection_size.json
etc/mongodb/collection_state.json
etc/mongodb/collections.json
etc/mongodb/connect_primary.json
etc/mongodb/connections.json
etc/mongodb/database_indexes.json
etc/mongodb/database_size.json
etc/mongodb/databases.json
etc/mongodb/flushing.json
etc/mongodb/index_miss_ratio.json
etc/mongodb/journal_commits_in_wl.json
etc/mongodb/journaled.json
etc/mongodb/last_flush_time.json
etc/mongodb/lock.json
etc/mongodb/memory.json
etc/mongodb/memory_mapped.json
etc/mongodb/mongodb.json
etc/mongodb/oplog.json
etc/mongodb/page_faults.json
etc/mongodb/queries_per_second.json
etc/mongodb/queues.json
etc/mongodb/replica_primary.json
etc/mongodb/write_data_files.json
etc/mysql/bufferpool-hitrate.json
etc/mysql/bufferpool-wait-free.json
etc/mysql/clients-aborted.json
etc/mysql/connects-aborted.json
etc/mysql/index-usage.json
etc/mysql/keycache-hitrate.json
etc/mysql/log-waits.json
etc/mysql/long-running-procs.json
etc/mysql/mysql.json
etc/mysql/open-files.json
etc/mysql/qcache-hitrate.json
etc/mysql/qcache-lowmem-prunes.json
etc/mysql/slow-queries.json
etc/mysql/table-fragmentation.json
etc/mysql/table-lock-contention.json
etc/mysql/tablecache-hitrate.json
etc/mysql/threadcache-hitrate.json
etc/mysql/threads-cached.json
etc/mysql/threads-connected.json
etc/mysql/threads-created.json
etc/mysql/threads-running.json
etc/mysql/tmp-disk-tables.json
etc/redis/redis.json
